panphon/__init__.py
panphon/_panphon.py
panphon/collapse.py
panphon/distance.py
panphon/errors.py
panphon/featuretable.py
panphon/panphonvec.py
panphon/permissive.py
panphon/segment.py
panphon/sonority.py
panphon/xsampa.py
panphon/data/asjp.yml
panphon/data/diacritic_definitions.yml
panphon/data/diacritic_definitions_schema.yml
panphon/data/dolgopolsky_prime.yml
panphon/data/feature_weights.csv
panphon/data/ipa-xsampa.csv
panphon/data/ipa_all.csv
panphon/data/ipa_bases.csv
panphon/data/sort_order.yml
panphon/data/sort_order_schema.yml
panphon-0.22.1.data/scripts/align_wordlists.py
panphon-0.22.1.data/scripts/generate_ipa_all.py
panphon-0.22.1.data/scripts/validate_ipa.py
panphon-0.22.1.dist-info/licenses/LICENSE.txt
panphon-0.22.1.dist-info/METADATA
panphon-0.22.1.dist-info/WHEEL
panphon-0.22.1.dist-info/top_level.txt
panphon-0.22.1.dist-info/zip-safe
panphon-0.22.1.dist-info/RECORD
